[{"i":"U+2E80","t":"CJK Radical Repeat","g":"CJK Radicals Supplement"},{"i":"U+2E81","t":"CJK Radical Cliff","g":"CJK Radicals Supplement"},{"i":"U+2E82","t":"CJK Radical Second One","g":"CJK Radicals Supplement"},{"i":"U+2E83","t":"CJK Radical Second Two","g":"CJK Radicals Supplement"},{"i":"U+2E84","t":"CJK Radical Second Three","g":"CJK Radicals Supplement"},{"i":"U+2E85","t":"CJK Radical Person","g":"CJK Radicals Supplement"},{"i":"U+2E86","t":"CJK Radical Box","g":"CJK Radicals Supplement"},{"i":"U+2E87","t":"CJK Radical Table","g":"CJK Radicals Supplement"},{"i":"U+2E88","t":"CJK Radical Knife One","g":"CJK Radicals Supplement"},{"i":"U+2E89","t":"CJK Radical Knife Two","g":"CJK Radicals Supplement"},{"i":"U+2E8A","t":"CJK Radical Divination","g":"CJK Radicals Supplement"},{"i":"U+2E8B","t":"CJK Radical Seal","g":"CJK Radicals Supplement"},{"i":"U+2E8C","t":"CJK Radical Small One","g":"CJK Radicals Supplement"},{"i":"U+2E8D","t":"CJK Radical Small Two","g":"CJK Radicals Supplement"},{"i":"U+2E8E","t":"CJK Radical Lame One","g":"CJK Radicals Supplement"},{"i":"U+2E8F","t":"CJK Radical Lame Two","g":"CJK Radicals Supplement"},{"i":"U+2E90","t":"CJK Radical Lame Three","g":"CJK Radicals Supplement"},{"i":"U+2E91","t":"CJK Radical Lame Four","g":"CJK Radicals Supplement"},{"i":"U+2E92","t":"CJK Radical Snake","g":"CJK Radicals Supplement"},{"i":"U+2E93","t":"CJK Radical Thread","g":"CJK Radicals Supplement"},{"i":"U+2E94","t":"CJK Radical Snout One","g":"CJK Radicals Supplement"},{"i":"U+2E95","t":"CJK Radical Snout Two","g":"CJK Radicals Supplement"},{"i":"U+2E96","t":"CJK Radical Heart One","g":"CJK Radicals Supplement"},{"i":"U+2E97","t":"CJK Radical Heart Two","g":"CJK Radicals Supplement"},{"i":"U+2E98","t":"CJK Radical Hand","g":"CJK Radicals Supplement"},{"i":"U+2E99","t":"CJK Radical Rap","g":"CJK Radicals Supplement"},{"i":"U+2E9A","t":"","g":"CJK Radicals Supplement"},{"i":"U+2E9B","t":"CJK Radical Choke","g":"CJK Radicals Supplement"},{"i":"U+2E9C","t":"CJK Radical Sun","g":"CJK Radicals Supplement"},{"i":"U+2E9D","t":"CJK Radical Moon","g":"CJK Radicals Supplement"},{"i":"U+2E9E","t":"CJK Radical Death","g":"CJK Radicals Supplement"},{"i":"U+2E9F","t":"CJK Radical Mother","g":"CJK Radicals Supplement"},{"i":"U+2EA0","t":"CJK Radical Civilian","g":"CJK Radicals Supplement"},{"i":"U+2EA1","t":"CJK Radical Water One","g":"CJK Radicals Supplement"},{"i":"U+2EA2","t":"CJK Radical Water Two","g":"CJK Radicals Supplement"},{"i":"U+2EA3","t":"CJK Radical Fire","g":"CJK Radicals Supplement"},{"i":"U+2EA4","t":"CJK Radical Paw One","g":"CJK Radicals Supplement"},{"i":"U+2EA5","t":"CJK Radical Paw Two","g":"CJK Radicals Supplement"},{"i":"U+2EA6","t":"CJK Radical Simplified Half Tree Trunk","g":"CJK Radicals Supplement"},{"i":"U+2EA7","t":"CJK Radical Cow","g":"CJK Radicals Supplement"},{"i":"U+2EA8","t":"CJK Radical Dog","g":"CJK Radicals Supplement"},{"i":"U+2EA9","t":"CJK Radical Jade","g":"CJK Radicals Supplement"},{"i":"U+2EAA","t":"CJK Radical Bolt of Cloth","g":"CJK Radicals Supplement"},{"i":"U+2EAB","t":"CJK Radical Eye","g":"CJK Radicals Supplement"},{"i":"U+2EAC","t":"CJK Radical Spirit One","g":"CJK Radicals Supplement"},{"i":"U+2EAD","t":"CJK Radical Spirit Two","g":"CJK Radicals Supplement"},{"i":"U+2EAE","t":"CJK Radical Bamboo","g":"CJK Radicals Supplement"},{"i":"U+2EAF","t":"CJK Radical Silk","g":"CJK Radicals Supplement"},{"i":"U+2EB0","t":"CJK Radical C-Simplified Silk","g":"CJK Radicals Supplement"},{"i":"U+2EB1","t":"CJK Radical Net One","g":"CJK Radicals Supplement"},{"i":"U+2EB2","t":"CJK Radical Net Two","g":"CJK Radicals Supplement"},{"i":"U+2EB3","t":"CJK Radical Net Three","g":"CJK Radicals Supplement"},{"i":"U+2EB4","t":"CJK Radical Net Four","g":"CJK Radicals Supplement"},{"i":"U+2EB5","t":"CJK Radical Mesh","g":"CJK Radicals Supplement"},{"i":"U+2EB6","t":"CJK Radical Sheep","g":"CJK Radicals Supplement"},{"i":"U+2EB7","t":"CJK Radical Ram","g":"CJK Radicals Supplement"},{"i":"U+2EB8","t":"CJK Radical Ewe","g":"CJK Radicals Supplement"},{"i":"U+2EB9","t":"CJK Radical Old","g":"CJK Radicals Supplement"},{"i":"U+2EBA","t":"CJK Radical Brush One","g":"CJK Radicals Supplement"},{"i":"U+2EBB","t":"CJK Radical Brush Two","g":"CJK Radicals Supplement"},{"i":"U+2EBC","t":"CJK Radical Meat","g":"CJK Radicals Supplement"},{"i":"U+2EBD","t":"CJK Radical Mortar","g":"CJK Radicals Supplement"},{"i":"U+2EBE","t":"CJK Radical Grass One","g":"CJK Radicals Supplement"},{"i":"U+2EBF","t":"CJK Radical Grass Two","g":"CJK Radicals Supplement"},{"i":"U+2EC0","t":"CJK Radical Grass Three","g":"CJK Radicals Supplement"},{"i":"U+2EC1","t":"CJK Radical Tiger","g":"CJK Radicals Supplement"},{"i":"U+2EC2","t":"CJK Radical Clothes","g":"CJK Radicals Supplement"},{"i":"U+2EC3","t":"CJK Radical West One","g":"CJK Radicals Supplement"},{"i":"U+2EC4","t":"CJK Radical West Two","g":"CJK Radicals Supplement"},{"i":"U+2EC5","t":"CJK Radical C-Simplified See","g":"CJK Radicals Supplement"},{"i":"U+2EC6","t":"CJK Radical Simplified Horn","g":"CJK Radicals Supplement"},{"i":"U+2EC7","t":"CJK Radical Horn","g":"CJK Radicals Supplement"},{"i":"U+2EC8","t":"CJK Radical C-Simplified Speech","g":"CJK Radicals Supplement"},{"i":"U+2EC9","t":"CJK Radical C-Simplified Shell","g":"CJK Radicals Supplement"},{"i":"U+2ECA","t":"CJK Radical Foot","g":"CJK Radicals Supplement"},{"i":"U+2ECB","t":"CJK Radical C-Simplified Cart","g":"CJK Radicals Supplement"},{"i":"U+2ECC","t":"CJK Radical Simplified Walk","g":"CJK Radicals Supplement"},{"i":"U+2ECD","t":"CJK Radical Walk One","g":"CJK Radicals Supplement"},{"i":"U+2ECE","t":"CJK Radical Walk Two","g":"CJK Radicals Supplement"},{"i":"U+2ECF","t":"CJK Radical City","g":"CJK Radicals Supplement"},{"i":"U+2ED0","t":"CJK Radical C-Simplified Gold","g":"CJK Radicals Supplement"},{"i":"U+2ED1","t":"CJK Radical Long One","g":"CJK Radicals Supplement"},{"i":"U+2ED2","t":"CJK Radical Long Two","g":"CJK Radicals Supplement"},{"i":"U+2ED3","t":"CJK Radical C-Simplified Long","g":"CJK Radicals Supplement"},{"i":"U+2ED4","t":"CJK Radical C-Simplified Gate","g":"CJK Radicals Supplement"},{"i":"U+2ED5","t":"CJK Radical Mound One","g":"CJK Radicals Supplement"},{"i":"U+2ED6","t":"CJK Radical Mound Two","g":"CJK Radicals Supplement"},{"i":"U+2ED7","t":"CJK Radical Rain","g":"CJK Radicals Supplement"},{"i":"U+2ED8","t":"CJK Radical Blue","g":"CJK Radicals Supplement"},{"i":"U+2ED9","t":"CJK Radical C-Simplified Tanned Leather","g":"CJK Radicals Supplement"},{"i":"U+2EDA","t":"CJK Radical C-Simplified Leaf","g":"CJK Radicals Supplement"},{"i":"U+2EDB","t":"CJK Radical C-Simplified Wind","g":"CJK Radicals Supplement"},{"i":"U+2EDC","t":"CJK Radical C-Simplified Fly","g":"CJK Radicals Supplement"},{"i":"U+2EDD","t":"CJK Radical Eat One","g":"CJK Radicals Supplement"},{"i":"U+2EDE","t":"CJK Radical Eat Two","g":"CJK Radicals Supplement"},{"i":"U+2EDF","t":"CJK Radical Eat Three","g":"CJK Radicals Supplement"},{"i":"U+2EE0","t":"CJK Radical C-Simplified Eat","g":"CJK Radicals Supplement"},{"i":"U+2EE1","t":"CJK Radical Head","g":"CJK Radicals Supplement"},{"i":"U+2EE2","t":"CJK Radical C-Simplified Horse","g":"CJK Radicals Supplement"},{"i":"U+2EE3","t":"CJK Radical Bone","g":"CJK Radicals Supplement"},{"i":"U+2EE4","t":"CJK Radical Ghost","g":"CJK Radicals Supplement"},{"i":"U+2EE5","t":"CJK Radical C-Simplified Fish","g":"CJK Radicals Supplement"},{"i":"U+2EE6","t":"CJK Radical C-Simplified Bird","g":"CJK Radicals Supplement"},{"i":"U+2EE7","t":"CJK Radical C-Simplified Salt","g":"CJK Radicals Supplement"},{"i":"U+2EE8","t":"CJK Radical Simplified Wheat","g":"CJK Radicals Supplement"},{"i":"U+2EE9","t":"CJK Radical Simplified Yellow","g":"CJK Radicals Supplement"},{"i":"U+2EEA","t":"CJK Radical C-Simplified Frog","g":"CJK Radicals Supplement"},{"i":"U+2EEB","t":"CJK Radical J-Simplified Even","g":"CJK Radicals Supplement"},{"i":"U+2EEC","t":"CJK Radical C-Simplified Even","g":"CJK Radicals Supplement"},{"i":"U+2EED","t":"CJK Radical J-Simplified Tooth","g":"CJK Radicals Supplement"},{"i":"U+2EEE","t":"CJK Radical C-Simplified Tooth","g":"CJK Radicals Supplement"},{"i":"U+2EEF","t":"CJK Radical J-Simplified Dragon","g":"CJK Radicals Supplement"},{"i":"U+2EF0","t":"CJK Radical C-Simplified Dragon","g":"CJK Radicals Supplement"},{"i":"U+2EF1","t":"CJK Radical Turtle","g":"CJK Radicals Supplement"},{"i":"U+2EF2","t":"CJK Radical J-Simplified Turtle","g":"CJK Radicals Supplement"},{"i":"U+2EF3","t":"CJK Radical C-Simplified Turtle","g":"CJK Radicals Supplement"},{"i":"U+2EF4","t":"","g":"CJK Radicals Supplement"},{"i":"U+2EF5","t":"","g":"CJK Radicals Supplement"},{"i":"U+2EF6","t":"","g":"CJK Radicals Supplement"},{"i":"U+2EF7","t":"","g":"CJK Radicals Supplement"},{"i":"U+2EF8","t":"","g":"CJK Radicals Supplement"},{"i":"U+2EF9","t":"","g":"CJK Radicals Supplement"},{"i":"U+2EFA","t":"","g":"CJK Radicals Supplement"},{"i":"U+2EFB","t":"","g":"CJK Radicals Supplement"},{"i":"U+2EFC","t":"","g":"CJK Radicals Supplement"},{"i":"U+2EFD","t":"","g":"CJK Radicals Supplement"},{"i":"U+2EFE","t":"","g":"CJK Radicals Supplement"},{"i":"U+2EFF","t":"","g":"CJK Radicals Supplement"}]