[{"i":"U+2700","t":"Black Safety Scissors","g":"Dingbats"},{"i":"U+2701","t":"Upper Blade Scissors","g":"Dingbats"},{"i":"U+2702","t":"Black Scissors","g":"Dingbats"},{"i":"U+2703","t":"Lower Blade Scissors","g":"Dingbats"},{"i":"U+2704","t":"White Scissors","g":"Dingbats"},{"i":"U+2705","t":"White Heavy Check Mark","g":"Dingbats"},{"i":"U+2706","t":"Telephone Location Sign","g":"Dingbats"},{"i":"U+2707","t":"Tape Drive","g":"Dingbats"},{"i":"U+2708","t":"Airplane","g":"Dingbats"},{"i":"U+2709","t":"Envelope","g":"Dingbats"},{"i":"U+270A","t":"Raised Fist","g":"Dingbats"},{"i":"U+270B","t":"Raised Hand","g":"Dingbats"},{"i":"U+270C","t":"Victory Hand","g":"Dingbats"},{"i":"U+270D","t":"Writing Hand","g":"Dingbats"},{"i":"U+270E","t":"Lower Right Pencil","g":"Dingbats"},{"i":"U+270F","t":"Pencil","g":"Dingbats"},{"i":"U+2710","t":"Upper Right Pencil","g":"Dingbats"},{"i":"U+2711","t":"White Nib","g":"Dingbats"},{"i":"U+2712","t":"Black Nib","g":"Dingbats"},{"i":"U+2713","t":"Check Mark","g":"Dingbats"},{"i":"U+2714","t":"Heavy Check Mark","g":"Dingbats"},{"i":"U+2715","t":"Multiplication X","g":"Dingbats"},{"i":"U+2716","t":"Heavy Multiplication X","g":"Dingbats"},{"i":"U+2717","t":"Ballot X","g":"Dingbats"},{"i":"U+2718","t":"Heavy Ballot X","g":"Dingbats"},{"i":"U+2719","t":"Outlined Greek Cross","g":"Dingbats"},{"i":"U+271A","t":"Heavy Greek Cross","g":"Dingbats"},{"i":"U+271B","t":"Open Centre Cross","g":"Dingbats"},{"i":"U+271C","t":"Heavy Open Centre Cross","g":"Dingbats"},{"i":"U+271D","t":"Latin Cross","g":"Dingbats"},{"i":"U+271E","t":"Shadowed White Latin Cross","g":"Dingbats"},{"i":"U+271F","t":"Outlined Latin Cross","g":"Dingbats"},{"i":"U+2720","t":"Maltese Cross","g":"Dingbats"},{"i":"U+2721","t":"Star of David","g":"Dingbats"},{"i":"U+2722","t":"Four Teardrop-Spoked Asterisk","g":"Dingbats"},{"i":"U+2723","t":"Four Balloon-Spoked Asterisk","g":"Dingbats"},{"i":"U+2724","t":"Heavy Four Balloon-Spoked Asterisk","g":"Dingbats"},{"i":"U+2725","t":"Four Club-Spoked Asterisk","g":"Dingbats"},{"i":"U+2726","t":"Black Four Pointed Star","g":"Dingbats"},{"i":"U+2727","t":"White Four Pointed Star","g":"Dingbats"},{"i":"U+2728","t":"Sparkles","g":"Dingbats"},{"i":"U+2729","t":"Stress Outlined White Star","g":"Dingbats"},{"i":"U+272A","t":"Circled White Star","g":"Dingbats"},{"i":"U+272B","t":"Open Centre Black Star","g":"Dingbats"},{"i":"U+272C","t":"Black Centre White Star","g":"Dingbats"},{"i":"U+272D","t":"Outlined Black Star","g":"Dingbats"},{"i":"U+272E","t":"Heavy Outlined Black Star","g":"Dingbats"},{"i":"U+272F","t":"Pinwheel Star","g":"Dingbats"},{"i":"U+2730","t":"Shadowed White Star","g":"Dingbats"},{"i":"U+2731","t":"Heavy Asterisk","g":"Dingbats"},{"i":"U+2732","t":"Open Centre Asterisk","g":"Dingbats"},{"i":"U+2733","t":"Eight Spoked Asterisk","g":"Dingbats"},{"i":"U+2734","t":"Eight Pointed Black Star","g":"Dingbats"},{"i":"U+2735","t":"Eight Pointed Pinwheel Star","g":"Dingbats"},{"i":"U+2736","t":"Six Pointed Black Star","g":"Dingbats"},{"i":"U+2737","t":"Eight Pointed Rectilinear Black Star","g":"Dingbats"},{"i":"U+2738","t":"Heavy Eight Pointed Rectilinear Black Star","g":"Dingbats"},{"i":"U+2739","t":"Twelve Pointed Black Star","g":"Dingbats"},{"i":"U+273A","t":"Sixteen Pointed Asterisk","g":"Dingbats"},{"i":"U+273B","t":"Teardrop-Spoked Asterisk","g":"Dingbats"},{"i":"U+273C","t":"Open Centre Teardrop-Spoked Asterisk","g":"Dingbats"},{"i":"U+273D","t":"Heavy Teardrop-Spoked Asterisk","g":"Dingbats"},{"i":"U+273E","t":"Six Petalled Black and White Florette","g":"Dingbats"},{"i":"U+273F","t":"Black Florette","g":"Dingbats"},{"i":"U+2740","t":"White Florette","g":"Dingbats"},{"i":"U+2741","t":"Eight Petalled Outlined Black Florette","g":"Dingbats"},{"i":"U+2742","t":"Circled Open Centre Eight Pointed Star","g":"Dingbats"},{"i":"U+2743","t":"Heavy Teardrop-Spoked Pinwheel Asterisk","g":"Dingbats"},{"i":"U+2744","t":"Snowflake","g":"Dingbats"},{"i":"U+2745","t":"Tight Trifoliate Snowflake","g":"Dingbats"},{"i":"U+2746","t":"Heavy Chevron Snowflake","g":"Dingbats"},{"i":"U+2747","t":"Sparkle","g":"Dingbats"},{"i":"U+2748","t":"Heavy Sparkle","g":"Dingbats"},{"i":"U+2749","t":"Balloon-Spoked Asterisk","g":"Dingbats"},{"i":"U+274A","t":"Eight Teardrop-Spoked Propeller Asterisk","g":"Dingbats"},{"i":"U+274B","t":"Heavy Eight Teardrop-Spoked Propeller Asterisk","g":"Dingbats"},{"i":"U+274C","t":"Cross Mark","g":"Dingbats"},{"i":"U+274D","t":"Shadowed White Circle","g":"Dingbats"},{"i":"U+274E","t":"Negative Squared Cross Mark","g":"Dingbats"},{"i":"U+274F","t":"Lower Right Drop-Shadowed White Square","g":"Dingbats"},{"i":"U+2750","t":"Upper Right Drop-Shadowed White Square","g":"Dingbats"},{"i":"U+2751","t":"Lower Right Shadowed White Square","g":"Dingbats"},{"i":"U+2752","t":"Upper Right Shadowed White Square","g":"Dingbats"},{"i":"U+2753","t":"Black Question Mark Ornament","g":"Dingbats"},{"i":"U+2754","t":"White Question Mark Ornament","g":"Dingbats"},{"i":"U+2755","t":"White Exclamation Mark Ornament","g":"Dingbats"},{"i":"U+2756","t":"Black Diamond Minus White X","g":"Dingbats"},{"i":"U+2757","t":"Heavy Exclamation Mark Symbol","g":"Dingbats"},{"i":"U+2758","t":"Light Vertical Bar","g":"Dingbats"},{"i":"U+2759","t":"Medium Vertical Bar","g":"Dingbats"},{"i":"U+275A","t":"Heavy Vertical Bar","g":"Dingbats"},{"i":"U+275B","t":"Heavy Single Turned Comma Quotation Mark Ornament","g":"Dingbats"},{"i":"U+275C","t":"Heavy Single Comma Quotation Mark Ornament","g":"Dingbats"},{"i":"U+275D","t":"Heavy Double Turned Comma Quotation Mark Ornament","g":"Dingbats"},{"i":"U+275E","t":"Heavy Double Comma Quotation Mark Ornament","g":"Dingbats"},{"i":"U+275F","t":"Heavy Low Single Comma Quotation Mark Ornament","g":"Dingbats"},{"i":"U+2760","t":"Heavy Low Double Comma Quotation Mark Ornament","g":"Dingbats"},{"i":"U+2761","t":"Curved Stem Paragraph Sign Ornament","g":"Dingbats"},{"i":"U+2762","t":"Heavy Exclamation Mark Ornament","g":"Dingbats"},{"i":"U+2763","t":"Heavy Heart Exclamation Mark Ornament","g":"Dingbats"},{"i":"U+2764","t":"Black Heart Symbol","g":"Dingbats"},{"i":"U+2765","t":"Rotated Heavy Black Heart Bullet","g":"Dingbats"},{"i":"U+2766","t":"Floral Heart","g":"Dingbats"},{"i":"U+2767","t":"Rotated Floral Heart Bullet","g":"Dingbats"},{"i":"U+2768","t":"Medium Left Parenthesis Ornament","g":"Dingbats"},{"i":"U+2769","t":"Medium Right Parenthesis Ornament","g":"Dingbats"},{"i":"U+276A","t":"Medium Flattened Left Parenthesis Ornament","g":"Dingbats"},{"i":"U+276B","t":"Medium Flattened Right Parenthesis Ornament","g":"Dingbats"},{"i":"U+276C","t":"Medium Left-Pointing Angle Bracket Ornament","g":"Dingbats"},{"i":"U+276D","t":"Medium Right-Pointing Angle Bracket Ornament","g":"Dingbats"},{"i":"U+276E","t":"Heavy Left-Pointing Angle Quotation Mark Ornament","g":"Dingbats"},{"i":"U+276F","t":"Heavy Right-Pointing Angle Quotation Mark Ornament","g":"Dingbats"},{"i":"U+2770","t":"Heavy Left-Pointing Angle Bracket Ornament","g":"Dingbats"},{"i":"U+2771","t":"Heavy Right-Pointing Angle Bracket Ornament","g":"Dingbats"},{"i":"U+2772","t":"Light Left Tortoise Shell Bracket Ornament","g":"Dingbats"},{"i":"U+2773","t":"Light Right Tortoise Shell Bracket Ornament","g":"Dingbats"},{"i":"U+2774","t":"Medium Left Curly Bracket Ornament","g":"Dingbats"},{"i":"U+2775","t":"Medium Right Curly Bracket Ornament","g":"Dingbats"},{"i":"U+2776","t":"Dingbat Negative Circled Digit One","g":"Dingbats"},{"i":"U+2777","t":"Dingbat Negative Circled Digit Two","g":"Dingbats"},{"i":"U+2778","t":"Dingbat Negative Circled Digit Three","g":"Dingbats"},{"i":"U+2779","t":"Dingbat Negative Circled Digit Four","g":"Dingbats"},{"i":"U+277A","t":"Dingbat Negative Circled Digit Five","g":"Dingbats"},{"i":"U+277B","t":"Dingbat Negative Circled Digit Six","g":"Dingbats"},{"i":"U+277C","t":"Dingbat Negative Circled Digit Seven","g":"Dingbats"},{"i":"U+277D","t":"Dingbat Negative Circled Digit Eight","g":"Dingbats"},{"i":"U+277E","t":"Dingbat Negative Circled Digit Nine","g":"Dingbats"},{"i":"U+277F","t":"Dingbat Negative Circled Number Ten","g":"Dingbats"},{"i":"U+2780","t":"Dingbat Circled Sans-Serif Digit One","g":"Dingbats"},{"i":"U+2781","t":"Dingbat Circled Sans-Serif Digit Two","g":"Dingbats"},{"i":"U+2782","t":"Dingbat Circled Sans-Serif Digit Three","g":"Dingbats"},{"i":"U+2783","t":"Dingbat Circled Sans-Serif Digit Four","g":"Dingbats"},{"i":"U+2784","t":"Dingbat Circled Sans-Serif Digit Five","g":"Dingbats"},{"i":"U+2785","t":"Dingbat Circled Sans-Serif Digit Six","g":"Dingbats"},{"i":"U+2786","t":"Dingbat Circled Sans-Serif Digit Seven","g":"Dingbats"},{"i":"U+2787","t":"Dingbat Circled Sans-Serif Digit Eight","g":"Dingbats"},{"i":"U+2788","t":"Dingbat Circled Sans-Serif Digit Nine","g":"Dingbats"},{"i":"U+2789","t":"Dingbat Circled Sans-Serif Number Ten","g":"Dingbats"},{"i":"U+278A","t":"Dingbat Negative Circled Sans-Serif Digit One","g":"Dingbats"},{"i":"U+278B","t":"Dingbat Negative Circled Sans-Serif Digit Two","g":"Dingbats"},{"i":"U+278C","t":"Dingbat Negative Circled Sans-Serif Digit Three","g":"Dingbats"},{"i":"U+278D","t":"Dingbat Negative Circled Sans-Serif Digit Four","g":"Dingbats"},{"i":"U+278E","t":"Dingbat Negative Circled Sans-Serif Digit Five","g":"Dingbats"},{"i":"U+278F","t":"Dingbat Negative Circled Sans-Serif Digit Six","g":"Dingbats"},{"i":"U+2790","t":"Dingbat Negative Circled Sans-Serif Digit Seven","g":"Dingbats"},{"i":"U+2791","t":"Dingbat Negative Circled Sans-Serif Digit Eight","g":"Dingbats"},{"i":"U+2792","t":"Dingbat Negative Circled Sans-Serif Digit Nine","g":"Dingbats"},{"i":"U+2793","t":"Dingbat Negative Circled Sans-Serif Number Ten","g":"Dingbats"},{"i":"U+2794","t":"Heavy Wide-Headed Rightwards Arrow","g":"Dingbats"},{"i":"U+2795","t":"Heavy Plus Sign","g":"Dingbats"},{"i":"U+2796","t":"Heavy Minus Sign","g":"Dingbats"},{"i":"U+2797","t":"Heavy Division Sign","g":"Dingbats"},{"i":"U+2798","t":"Heavy South East Arrow","g":"Dingbats"},{"i":"U+2799","t":"Heavy Rightwards Arrow","g":"Dingbats"},{"i":"U+279A","t":"Heavy North East Arrow","g":"Dingbats"},{"i":"U+279B","t":"Drafting Point Rightwards Arrow","g":"Dingbats"},{"i":"U+279C","t":"Heavy Round-Tipped Rightwards Arrow","g":"Dingbats"},{"i":"U+279D","t":"Triangle-Headed Rightwards Arrow","g":"Dingbats"},{"i":"U+279E","t":"Heavy Triangle-Headed Rightwards Arrow","g":"Dingbats"},{"i":"U+279F","t":"Dashed Triangle-Headed Rightwards Arrow","g":"Dingbats"},{"i":"U+27A0","t":"Heavy Dashed Triangle-Headed Rightwards Arrow","g":"Dingbats"},{"i":"U+27A1","t":"Black Rightwards Arrow","g":"Dingbats"},{"i":"U+27A2","t":"Three-D Top-Lighted Rightwards Arrowhead","g":"Dingbats"},{"i":"U+27A3","t":"Three-D Bottom-Lighted Rightwards Arrowhead","g":"Dingbats"},{"i":"U+27A4","t":"Black Rightwards Arrowhead","g":"Dingbats"},{"i":"U+27A5","t":"Heavy Black Curved Downwards and Rightwards Arrow","g":"Dingbats"},{"i":"U+27A6","t":"Heavy Black Curved Upwards and Rightwards Arrow","g":"Dingbats"},{"i":"U+27A7","t":"Squat Black Rightwards Arrow","g":"Dingbats"},{"i":"U+27A8","t":"Heavy Concave-Pointed Black Rightwards Arrow","g":"Dingbats"},{"i":"U+27A9","t":"Right-Shaded White Rightwards Arrow","g":"Dingbats"},{"i":"U+27AA","t":"Left-Shaded White Rightwards Arrow","g":"Dingbats"},{"i":"U+27AB","t":"Back-Tilted Shadowed White Rightwards Arrow","g":"Dingbats"},{"i":"U+27AC","t":"Front-Tilted Shadowed White Rightwards Arrow","g":"Dingbats"},{"i":"U+27AD","t":"Heavy Lower Right-Shadowed White Rightwards Arrow","g":"Dingbats"},{"i":"U+27AE","t":"Heavy Upper Right-Shadowed White Rightwards Arrow","g":"Dingbats"},{"i":"U+27AF","t":"Notched Lower Right-Shadowed White Rightwards Arrow","g":"Dingbats"},{"i":"U+27B0","t":"Curly Loop","g":"Dingbats"},{"i":"U+27B1","t":"Notched Upper Right-Shadowed White Rightwards Arrow","g":"Dingbats"},{"i":"U+27B2","t":"Circled Heavy White Rightwards Arrow","g":"Dingbats"},{"i":"U+27B3","t":"White-Feathered Rightwards Arrow","g":"Dingbats"},{"i":"U+27B4","t":"Black-Feathered South East Arrow","g":"Dingbats"},{"i":"U+27B5","t":"Black-Feathered Rightwards Arrow","g":"Dingbats"},{"i":"U+27B6","t":"Black-Feathered North East Arrow","g":"Dingbats"},{"i":"U+27B7","t":"Heavy Black-Feathered South East Arrow","g":"Dingbats"},{"i":"U+27B8","t":"Heavy Black-Feathered Rightwards Arrow","g":"Dingbats"},{"i":"U+27B9","t":"Heavy Black-Feathered North East Arrow","g":"Dingbats"},{"i":"U+27BA","t":"Teardrop-Barbed Rightwards Arrow","g":"Dingbats"},{"i":"U+27BB","t":"Heavy Teardrop-Shanked Rightwards Arrow","g":"Dingbats"},{"i":"U+27BC","t":"Wedge-Tailed Rightwards Arrow","g":"Dingbats"},{"i":"U+27BD","t":"Heavy Wedge-Tailed Rightwards Arrow","g":"Dingbats"},{"i":"U+27BE","t":"Open-Outlined Rightwards Arrow","g":"Dingbats"},{"i":"U+27BF","t":"Double Curly Loop","g":"Dingbats"}]